<?xml version="1.0" encoding="UTF-8" standalone="no"?>
<event category="STEP" id="0">
  <actions>
    <action id="603" library="1">
      <!--action name: Code-->
      <kind>CODE</kind>
      <allowRelative>false</allowRelative>
      <question>false</question>
      <canApplyTo>true</canApplyTo>
      <actionType>CODE</actionType>
      <functionName/>
      <relative>false</relative>
      <not>false</not>
      <appliesTo>.self</appliesTo>
      <arguments>
        <argument kind="STRING">if (true)
{
    x += xVel;
    y += yVel;

    if (xVel &lt; 0) xVel += 0.1;
    
    if (yVel &lt; 6)
    {
        yVel += myGrav;
    }
    
    if (y &gt; 240)
        room_goto(rEnd3);
}</argument>
      </arguments>
    </action>
  </actions>
</event>
